[
  {
    "CompressionResults": [
      {
        "AfterBytes": 2468648121,
        "BeforeBytes": 3352401330,
        "CompType": 0,
        "TotalResults": 1
      }
    ],
    "Confidence": 0,
    "FolderName": "Wigmund",
    "GameName": "Wigmund",
    "PoorlyCompressedExtensions": {
      ".PNG": 9,
      ".cnv": 2,
      ".ini": 1,
      ".tps": 5,
      ".vdf": 1
    },
    "SteamID": 1164690,
    "TotalFiles": 1
  },
  {
    "CompressionResults": [
      {
        "AfterBytes": 21673705011,
        "BeforeBytes": 32195152221,
        "CompType": 0,
        "TotalResults": 3
      },
      {
        "AfterBytes": 21321829614,
        "BeforeBytes": 33394013731,
        "CompType": 1,
        "TotalResults": 3
      },
      {
        "AfterBytes": 20402256627,
        "BeforeBytes": 32467358195,
        "CompType": 2,
        "TotalResults": 3
      },
      {
        "AfterBytes": 20219128414,
        "BeforeBytes": 32471512419,
        "CompType": 3,
        "TotalResults": 6
      }
    ],
    "Confidence": 1,
    "FolderName": "Trepang2",
    "GameName": "Trepang2",
    "PoorlyCompressedExtensions": {
      ".lnk": 15,
      ".mp4": 222,
      ".png": 15,
      ".tps": 15,
      ".txt": 16
    },
    "SteamID": 1164940,
    "TotalFiles": 15
  },
  {
    "CompressionResults": [
      {
        "AfterBytes": 3904710375,
        "BeforeBytes": 9519695444,
        "CompType": 2,
        "TotalResults": 2
      }
    ],
    "Confidence": 0,
    "FolderName": "SistineVR",
    "GameName": "IL DIVINO - Michelangelo's Sistine Ceiling in VR",
    "PoorlyCompressedExtensions": {
      ".pdf": 2,
      ".txt": 2
    },
    "SteamID": 1165850,
    "TotalFiles": 2
  },
  {
    "CompressionResults": [
      {
        "AfterBytes": 97796103,
        "BeforeBytes": 117225963,
        "CompType": 3,
        "TotalResults": 1
      }
    ],
    "Confidence": 0,
    "FolderName": "6.0",
    "GameName": "6.0",
    "PoorlyCompressedExtensions": {
      ".pck": 1,
      ".txt": 1
    },
    "SteamID": 1165860,
    "TotalFiles": 1
  },
  {
    "CompressionResults": [
      {
        "AfterBytes": 1239865607,
        "BeforeBytes": 3060637581,
        "CompType": 0,
        "TotalResults": 1
      },
      {
        "AfterBytes": 844453575,
        "BeforeBytes": 2472631017,
        "CompType": 1,
        "TotalResults": 1
      }
    ],
    "Confidence": 0,
    "FolderName": "Death and Taxes",
    "GameName": "Death and Taxes",
    "PoorlyCompressedExtensions": {
      ".browser": 6,
      ".info": 2,
      ".map": 6,
      ".mp4": 6,
      ".resource": 10,
      ".txt": 2
    },
    "SteamID": 1166290,
    "TotalFiles": 2
  },
  {
    "CompressionResults": [
      {
        "AfterBytes": 3662130506,
        "BeforeBytes": 8333250332,
        "CompType": 2,
        "TotalResults": 1
      }
    ],
    "Confidence": 0,
    "FolderName": "Gloria Victis Siege",
    "GameName": "Siege Survival: Gloria Victis",
    "PoorlyCompressedExtensions": {
      ".aspx": 2,
      ".browser": 1,
      ".config": 4,
      ".info": 1,
      ".ini": 1,
      ".map": 1,
      ".txt": 1
    },
    "SteamID": 1167140,
    "TotalFiles": 1
  },
  {
    "CompressionResults": [
      {
        "AfterBytes": 4040077396,
        "BeforeBytes": 4476151882,
        "CompType": 0,
        "TotalResults": 5
      },
      {
        "AfterBytes": 4138912623,
        "BeforeBytes": 4657143448,
        "CompType": 1,
        "TotalResults": 8
      },
      {
        "AfterBytes": 3726618320,
        "BeforeBytes": 4135036124,
        "CompType": 2,
        "TotalResults": 16
      },
      {
        "AfterBytes": 3637625509,
        "BeforeBytes": 4147615471,
        "CompType": 3,
        "TotalResults": 17
      }
    ],
    "Confidence": 2,
    "FolderName": "Teardown",
    "GameName": "Teardown",
    "PoorlyCompressedExtensions": {
      ".bin": 5888,
      ".jpg": 15025,
      ".ogg": 9942,
      ".png": 28023,
      ".tde": 39884
    },
    "SteamID": 1167630,
    "TotalFiles": 46
  },
  {
    "CompressionResults": [
      {
        "AfterBytes": 582737741,
        "BeforeBytes": 1528624009,
        "CompType": 2,
        "TotalResults": 2
      }
    ],
    "Confidence": 0,
    "FolderName": "Orbital Bullet",
    "GameName": "Orbital Bullet",
    "PoorlyCompressedExtensions": {
      ".bank": 4,
      ".browser": 6,
      ".info": 2,
      ".map": 6,
      ".resource": 2,
      ".txt": 2
    },
    "SteamID": 1167680,
    "TotalFiles": 2
  },
  {
    "CompressionResults": [
      {
        "AfterBytes": 449764675,
        "BeforeBytes": 1430823134,
        "CompType": 3,
        "TotalResults": 1
      }
    ],
    "Confidence": 0,
    "FolderName": "Vampire's Fall Origins",
    "GameName": "Vampire's Fall: Origins",
    "PoorlyCompressedExtensions": {
      ".browser": 3,
      ".config": 7,
      ".info": 1,
      ".json": 1,
      ".map": 3,
      ".txt": 1,
      ".xml": 1
    },
    "SteamID": 1167950,
    "TotalFiles": 1
  },
  {
    "CompressionResults": [
      {
        "AfterBytes": 40073938,
        "BeforeBytes": 45496931,
        "CompType": 3,
        "TotalResults": 1
      }
    ],
    "Confidence": 0,
    "FolderName": "Knight Solitaire",
    "GameName": "Knight Solitaire",
    "PoorlyCompressedExtensions": {
      "": 49,
      ".plist": 1,
      ".png": 2
    },
    "SteamID": 1168060,
    "TotalFiles": 1
  },
  {
    "CompressionResults": [
      {
        "AfterBytes": 7770957063,
        "BeforeBytes": 7849337294,
        "CompType": 1,
        "TotalResults": 1
      },
      {
        "AfterBytes": 7759094271,
        "BeforeBytes": 7849336518,
        "CompType": 2,
        "TotalResults": 1
      }
    ],
    "Confidence": 0,
    "FolderName": "RESIDENT EVIL 2  BIOHAZARD RE2 R.P.D. Demo",
    "GameName": "Resident Evil 2 \"R.P.D. Demo\"",
    "PoorlyCompressedExtensions": {
      ".ini": 5,
      ".pak": 4
    },
    "SteamID": 1168280,
    "TotalFiles": 2
  },
  {
    "CompressionResults": [
      {
        "AfterBytes": 1337592513,
        "BeforeBytes": 1480667855,
        "CompType": 3,
        "TotalResults": 1
      }
    ],
    "Confidence": 0,
    "FolderName": "\u5343\u9762_Melancholy",
    "GameName": "\u5343\u9762 Melancholy Love",
    "PoorlyCompressedExtensions": {
      "": 2,
      ".txt": 1
    },
    "SteamID": 1168470,
    "TotalFiles": 1
  },
  {
    "CompressionResults": [
      {
        "AfterBytes": 138411352,
        "BeforeBytes": 141161609,
        "CompType": 2,
        "TotalResults": 1
      },
      {
        "AfterBytes": 137374575,
        "BeforeBytes": 141161609,
        "CompType": 3,
        "TotalResults": 1
      }
    ],
    "Confidence": 0,
    "FolderName": "MOLEK-SYNTEZ",
    "GameName": "MOLEK-SYNTEZ",
    "PoorlyCompressedExtensions": {
      ".cso": 14,
      ".csv": 2,
      ".dat": 2,
      ".glsl": 18,
      ".ogg": 52,
      ".png": 18
    },
    "SteamID": 1168880,
    "TotalFiles": 2
  },
  {
    "CompressionResults": [
      {
        "AfterBytes": 317599635,
        "BeforeBytes": 394736076,
        "CompType": 0,
        "TotalResults": 2
      },
      {
        "AfterBytes": 339695519,
        "BeforeBytes": 428327784,
        "CompType": 1,
        "TotalResults": 2
      },
      {
        "AfterBytes": 336553404,
        "BeforeBytes": 428891330,
        "CompType": 2,
        "TotalResults": 4
      },
      {
        "AfterBytes": 341537171,
        "BeforeBytes": 454181612,
        "CompType": 3,
        "TotalResults": 1
      }
    ],
    "Confidence": 0,
    "FolderName": "Necesse",
    "GameName": "Necesse",
    "PoorlyCompressedExtensions": {
      ".access": 9,
      ".bat": 12,
      ".certs": 9,
      ".cfg": 10,
      ".data": 5,
      ".ja": 9,
      ".json": 6,
      ".txt": 18
    },
    "SteamID": 1169040,
    "TotalFiles": 9
  },
  {
    "CompressionResults": [
      {
        "AfterBytes": 682975736,
        "BeforeBytes": 1676106198,
        "CompType": 3,
        "TotalResults": 1
      }
    ],
    "Confidence": 0,
    "FolderName": "Danger Scavenger",
    "GameName": "Danger Scavenger",
    "PoorlyCompressedExtensions": {
      ".bank": 2,
      ".browser": 3,
      ".caw": 14,
      ".config": 7,
      ".info": 1,
      ".map": 3,
      ".resource": 4,
      ".txt": 1,
      ".xml": 1
    },
    "SteamID": 1169740,
    "TotalFiles": 1
  },
  {
    "CompressionResults": [
      {
        "AfterBytes": 6685236140,
        "BeforeBytes": 7797127640,
        "CompType": 2,
        "TotalResults": 2
      }
    ],
    "Confidence": 0,
    "FolderName": "Boomerang X",
    "GameName": "Boomerang X",
    "PoorlyCompressedExtensions": {
      ".browser": 6,
      ".info": 2,
      ".map": 6,
      ".rsp": 2
    },
    "SteamID": 1170060,
    "TotalFiles": 2
  },
  {
    "CompressionResults": [
      {
        "AfterBytes": 1093280759,
        "BeforeBytes": 1674958684,
        "CompType": 1,
        "TotalResults": 1
      }
    ],
    "Confidence": 0,
    "FolderName": "Foretales",
    "GameName": "Foretales",
    "PoorlyCompressedExtensions": {
      ".browser": 3,
      ".info": 1,
      ".json": 2,
      ".map": 3,
      ".mp4": 21,
      ".txt": 1
    },
    "SteamID": 1170080,
    "TotalFiles": 1
  },
  {
    "CompressionResults": [
      {
        "AfterBytes": 3928907850,
        "BeforeBytes": 8447583854,
        "CompType": 3,
        "TotalResults": 1
      }
    ],
    "Confidence": 0,
    "FolderName": "PocketCars",
    "GameName": "Pocket Cars",
    "PoorlyCompressedExtensions": {
      ".browser": 3,
      ".info": 1,
      ".map": 3,
      ".resource": 10,
      ".txt": 1
    },
    "SteamID": 1170720,
    "TotalFiles": 1
  },
  {
    "CompressionResults": [
      {
        "AfterBytes": 2349666091,
        "BeforeBytes": 2656459688,
        "CompType": 0,
        "TotalResults": 1
      },
      {
        "AfterBytes": 2201889376,
        "BeforeBytes": 2656459688,
        "CompType": 3,
        "TotalResults": 1
      }
    ],
    "Confidence": 0,
    "FolderName": "XIII - Classic",
    "GameName": "XIII - Classic",
    "PoorlyCompressedExtensions": {
      ".FRT": 2,
      ".bik": 19,
      ".hsc": 40,
      ".scc": 2,
      ".txt": 2
    },
    "SteamID": 1170760,
    "TotalFiles": 2
  },
  {
    "CompressionResults": [
      {
        "AfterBytes": 5515626554,
        "BeforeBytes": 8563615311,
        "CompType": 2,
        "TotalResults": 1
      }
    ],
    "Confidence": 0,
    "FolderName": "Lust from Beyond - Prologue",
    "GameName": "Lust from Beyond: Prologue",
    "PoorlyCompressedExtensions": {
      ".bank": 4,
      ".browser": 3,
      ".info": 1,
      ".map": 3,
      ".pos": 15,
      ".resource": 1,
      ".txt": 1
    },
    "SteamID": 1170820,
    "TotalFiles": 1
  },
  {
    "CompressionResults": [
      {
        "AfterBytes": 289365236,
        "BeforeBytes": 320836227,
        "CompType": 3,
        "TotalResults": 1
      }
    ],
    "Confidence": 0,
    "FolderName": "Grimm's Hollow",
    "GameName": "Grimm's Hollow",
    "PoorlyCompressedExtensions": {
      ".ini": 1,
      ".mp3": 35,
      ".png": 357,
      ".r3proj": 1,
      ".xyz": 1
    },
    "SteamID": 1170880,
    "TotalFiles": 1
  },
  {
    "CompressionResults": [
      {
        "AfterBytes": 66109875753,
        "BeforeBytes": 74239237823,
        "CompType": 2,
        "TotalResults": 1
      },
      {
        "AfterBytes": 62821189209,
        "BeforeBytes": 72987537014,
        "CompType": 3,
        "TotalResults": 1
      }
    ],
    "Confidence": 0,
    "FolderName": "Mortal Online 2",
    "GameName": "Mortal Online 2",
    "PoorlyCompressedExtensions": {
      ".bat": 4,
      ".cer": 2,
      ".cur": 1,
      ".json": 2,
      ".mp4": 108,
      ".png": 2,
      ".sig": 1148,
      ".tps": 2,
      ".vdf": 2
    },
    "SteamID": 1170950,
    "TotalFiles": 2
  },
  {
    "CompressionResults": [
      {
        "AfterBytes": 7350847587,
        "BeforeBytes": 8846380967,
        "CompType": 1,
        "TotalResults": 1
      },
      {
        "AfterBytes": 4710267002,
        "BeforeBytes": 4956375577,
        "CompType": 3,
        "TotalResults": 1
      }
    ],
    "Confidence": 0,
    "FolderName": "Marbles on Stream",
    "GameName": "Marbles on Stream",
    "PoorlyCompressedExtensions": {
      ".cur": 1,
      ".mp4": 3,
      ".pak": 60,
      ".pem": 1,
      ".tps": 2
    },
    "SteamID": 1170970,
    "TotalFiles": 2
  },
  {
    "CompressionResults": [
      {
        "AfterBytes": 17222062655,
        "BeforeBytes": 17257891102,
        "CompType": 2,
        "TotalResults": 1
      },
      {
        "AfterBytes": 17182541580,
        "BeforeBytes": 17257891102,
        "CompType": 3,
        "TotalResults": 2
      }
    ],
    "Confidence": 0,
    "FolderName": "Valakas Story",
    "GameName": "Valakas Story",
    "PoorlyCompressedExtensions": {
      ".mp4": 6,
      ".pak": 3,
      ".txt": 3
    },
    "SteamID": 1171310,
    "TotalFiles": 3
  },
  {
    "CompressionResults": [
      {
        "AfterBytes": 400774595,
        "BeforeBytes": 511274926,
        "CompType": 3,
        "TotalResults": 1
      }
    ],
    "Confidence": 0,
    "FolderName": "Frog_Detective_3",
    "GameName": "Frog Detective 3: Corruption at Cowboy County",
    "PoorlyCompressedExtensions": {
      ".config": 1,
      ".info": 1,
      ".png": 2,
      ".txt": 1
    },
    "SteamID": 1171320,
    "TotalFiles": 1
  },
  {
    "CompressionResults": [
      {
        "AfterBytes": 62394683,
        "BeforeBytes": 295623306,
        "CompType": 2,
        "TotalResults": 1
      },
      {
        "AfterBytes": 70729147,
        "BeforeBytes": 318022779,
        "CompType": 3,
        "TotalResults": 1
      }
    ],
    "Confidence": 0,
    "FolderName": "The Supper",
    "GameName": "The Supper",
    "PoorlyCompressedExtensions": {
      ".browser": 6,
      ".info": 2,
      ".map": 6,
      ".resource": 20,
      ".txt": 2
    },
    "SteamID": 1171370,
    "TotalFiles": 2
  },
  {
    "CompressionResults": [
      {
        "AfterBytes": 41018108856,
        "BeforeBytes": 54317571936,
        "CompType": 0,
        "TotalResults": 2
      },
      {
        "AfterBytes": 36326793624,
        "BeforeBytes": 64884712225,
        "CompType": 1,
        "TotalResults": 1
      },
      {
        "AfterBytes": 50527940755,
        "BeforeBytes": 55015481223,
        "CompType": 2,
        "TotalResults": 3
      }
    ],
    "Confidence": 0,
    "FolderName": "Wayfinder",
    "GameName": "Wayfinder",
    "PoorlyCompressedExtensions": {
      ".bat": 12,
      ".json": 5,
      ".mkv": 13,
      ".mp4": 739,
      ".png": 7,
      ".tps": 6,
      ".xml": 5
    },
    "SteamID": 1171690,
    "TotalFiles": 6
  },
  {
    "CompressionResults": [
      {
        "AfterBytes": 1609229086,
        "BeforeBytes": 3150332895,
        "CompType": 3,
        "TotalResults": 1
      }
    ],
    "Confidence": 0,
    "FolderName": "Mona Lisa Beyond The Glass",
    "GameName": "Mona Lisa: Beyond The Glass",
    "PoorlyCompressedExtensions": {
      ".browser": 3,
      ".info": 1,
      ".lic": 1,
      ".map": 3,
      ".png": 3,
      ".resource": 2
    },
    "SteamID": 1172310,
    "TotalFiles": 1
  },
  {
    "CompressionResults": [
      {
        "AfterBytes": 46399906451,
        "BeforeBytes": 55300420536,
        "CompType": 0,
        "TotalResults": 2
      },
      {
        "AfterBytes": 54551052983,
        "BeforeBytes": 55321976136,
        "CompType": 1,
        "TotalResults": 3
      },
      {
        "AfterBytes": 56160203455,
        "BeforeBytes": 56950949491,
        "CompType": 2,
        "TotalResults": 9
      },
      {
        "AfterBytes": 56766117226,
        "BeforeBytes": 58156546047,
        "CompType": 3,
        "TotalResults": 5
      }
    ],
    "Confidence": 2,
    "FolderName": "Jedi Fallen Order",
    "GameName": "STAR WARS Jedi: Fallen Order\u2122 ",
    "PoorlyCompressedExtensions": {
      ".bin": 139,
      ".cab": 2926,
      ".ini": 19,
      ".json": 20,
      ".mp4": 435,
      ".pak": 1654,
      ".png": 19
    },
    "SteamID": 1172380,
    "TotalFiles": 19
  },
  {
    "CompressionResults": [
      {
        "AfterBytes": 409348361,
        "BeforeBytes": 2028117177,
        "CompType": 3,
        "TotalResults": 1
      }
    ],
    "Confidence": 0,
    "FolderName": "Carto",
    "GameName": "Carto",
    "PoorlyCompressedExtensions": {
      ".bank": 2,
      ".browser": 3,
      ".info": 1,
      ".map": 3,
      ".resource": 3,
      ".txt": 1
    },
    "SteamID": 1172450,
    "TotalFiles": 1
  },
  {
    "CompressionResults": [
      {
        "AfterBytes": 70641686808,
        "BeforeBytes": 71503510696,
        "CompType": 0,
        "TotalResults": 99
      },
      {
        "AfterBytes": 71721952647,
        "BeforeBytes": 73264905585,
        "CompType": 1,
        "TotalResults": 82
      },
      {
        "AfterBytes": 71347504118,
        "BeforeBytes": 72659074564,
        "CompType": 2,
        "TotalResults": 101
      },
      {
        "AfterBytes": 70990358832,
        "BeforeBytes": 73387504183,
        "CompType": 3,
        "TotalResults": 69
      }
    ],
    "Confidence": 2,
    "FolderName": "Apex Legends",
    "GameName": "Apex Legends",
    "PoorlyCompressedExtensions": {
      ".bik": 85484,
      ".cer": 351,
      ".mstr": 1602,
      ".png": 357,
      ".rpak": 917063,
      ".starpak": 740018,
      ".vdf": 349
    },
    "SteamID": 1172470,
    "TotalFiles": 351
  },
  {
    "CompressionResults": [
      {
        "AfterBytes": 79495239,
        "BeforeBytes": 180267648,
        "CompType": 2,
        "TotalResults": 1
      },
      {
        "AfterBytes": 68280391,
        "BeforeBytes": 180267648,
        "CompType": 3,
        "TotalResults": 1
      }
    ],
    "Confidence": 0,
    "FolderName": "Hang The Kings",
    "GameName": "Hang The Kings",
    "PoorlyCompressedExtensions": {
      ".browser": 6,
      ".info": 2,
      ".map": 6
    },
    "SteamID": 1172500,
    "TotalFiles": 2
  },
  {
    "CompressionResults": [
      {
        "AfterBytes": 85295177,
        "BeforeBytes": 192780422,
        "CompType": 2,
        "TotalResults": 1
      },
      {
        "AfterBytes": 73052233,
        "BeforeBytes": 192780422,
        "CompType": 3,
        "TotalResults": 1
      }
    ],
    "Confidence": 0,
    "FolderName": "Unlock The King",
    "GameName": "Unlock The King",
    "PoorlyCompressedExtensions": {
      ".browser": 6,
      ".info": 2,
      ".map": 6
    },
    "SteamID": 1172510,
    "TotalFiles": 2
  },
  {
    "CompressionResults": [
      {
        "AfterBytes": 87724100,
        "BeforeBytes": 187313531,
        "CompType": 3,
        "TotalResults": 1
      }
    ],
    "Confidence": 0,
    "FolderName": "Colorgrid",
    "GameName": "Colorgrid",
    "PoorlyCompressedExtensions": {
      ".browser": 6,
      ".icns": 1,
      ".info": 2,
      ".map": 6,
      ".meta": 4,
      ".plist": 3,
      ".resource": 2
    },
    "SteamID": 1172520,
    "TotalFiles": 1
  },
  {
    "CompressionResults": [
      {
        "AfterBytes": 40634563,
        "BeforeBytes": 207504468,
        "CompType": 3,
        "TotalResults": 1
      }
    ],
    "Confidence": 0,
    "FolderName": "Daylife in Japan - Animated Jigsaw Puzzle Series",
    "GameName": "Daylife in Japan - Animated Jigsaw Puzzle Series",
    "PoorlyCompressedExtensions": {
      ".browser": 3,
      ".info": 1,
      ".map": 3,
      ".resource": 1
    },
    "SteamID": 1172530,
    "TotalFiles": 1
  },
  {
    "CompressionResults": [
      {
        "AfterBytes": 108160816300,
        "BeforeBytes": 108395039219,
        "CompType": 0,
        "TotalResults": 11
      },
      {
        "AfterBytes": 104131385063,
        "BeforeBytes": 104416410364,
        "CompType": 1,
        "TotalResults": 21
      },
      {
        "AfterBytes": 104165904989,
        "BeforeBytes": 104501679099,
        "CompType": 2,
        "TotalResults": 35
      },
      {
        "AfterBytes": 110404723708,
        "BeforeBytes": 110855641444,
        "CompType": 3,
        "TotalResults": 23
      }
    ],
    "Confidence": 2,
    "FolderName": "Sea of Thieves",
    "GameName": "Sea of Thieves",
    "PoorlyCompressedExtensions": {
      ".bin": 164,
      ".m3u8": 462,
      ".manifest": 90,
      ".pak": 180761,
      ".vdf": 85,
      ".version": 56
    },
    "SteamID": 1172620,
    "TotalFiles": 90
  },
  {
    "CompressionResults": [
      {
        "AfterBytes": 9366209479,
        "BeforeBytes": 9458390992,
        "CompType": 0,
        "TotalResults": 2
      },
      {
        "AfterBytes": 9338428389,
        "BeforeBytes": 9477957411,
        "CompType": 2,
        "TotalResults": 1
      },
      {
        "AfterBytes": 9282905061,
        "BeforeBytes": 9478707687,
        "CompType": 3,
        "TotalResults": 2
      }
    ],
    "Confidence": 0,
    "FolderName": "Industria",
    "GameName": "INDUSTRIA",
    "PoorlyCompressedExtensions": {
      ".mp4": 24,
      ".pak": 10,
      ".tps": 5,
      ".txt": 10
    },
    "SteamID": 1172650,
    "TotalFiles": 5
  },
  {
    "CompressionResults": [
      {
        "AfterBytes": 104727333,
        "BeforeBytes": 452316723,
        "CompType": 3,
        "TotalResults": 1
      }
    ],
    "Confidence": 0,
    "FolderName": "Doubles Hard RDS",
    "GameName": "Doubles Hard",
    "PoorlyCompressedExtensions": {
      ".browser": 3,
      ".info": 1,
      ".map": 3,
      ".png": 1,
      ".resource": 2
    },
    "SteamID": 1172720,
    "TotalFiles": 1
  },
  {
    "CompressionResults": [
      {
        "AfterBytes": 1863946603,
        "BeforeBytes": 1884947702,
        "CompType": 1,
        "TotalResults": 1
      }
    ],
    "Confidence": 0,
    "FolderName": "Cockwork Industries",
    "GameName": "Cockwork Industries Complete",
    "PoorlyCompressedExtensions": {
      ".ini": 1,
      ".jpg": 50,
      ".txt": 1,
      ".vis": 2,
      ".vv": 1
    },
    "SteamID": 1172940,
    "TotalFiles": 1
  },
  {
    "CompressionResults": [
      {
        "AfterBytes": 545646166,
        "BeforeBytes": 1159059676,
        "CompType": 0,
        "TotalResults": 1
      },
      {
        "AfterBytes": 543426634,
        "BeforeBytes": 1229183462,
        "CompType": 1,
        "TotalResults": 1
      },
      {
        "AfterBytes": 524118113,
        "BeforeBytes": 1229218162,
        "CompType": 2,
        "TotalResults": 1
      },
      {
        "AfterBytes": 465623137,
        "BeforeBytes": 1229138800,
        "CompType": 3,
        "TotalResults": 1
      }
    ],
    "Confidence": 0,
    "FolderName": "Metal Unit",
    "GameName": "Metal Unit",
    "PoorlyCompressedExtensions": {
      ".browser": 12,
      ".info": 4,
      ".map": 12,
      ".png": 16,
      ".resource": 12,
      ".txt": 14
    },
    "SteamID": 1173200,
    "TotalFiles": 4
  },
  {
    "CompressionResults": [
      {
        "AfterBytes": 10332986058,
        "BeforeBytes": 17596775459,
        "CompType": 2,
        "TotalResults": 1
      },
      {
        "AfterBytes": 7611252742,
        "BeforeBytes": 15139087194,
        "CompType": 3,
        "TotalResults": 1
      }
    ],
    "Confidence": 0,
    "FolderName": "Bleak Faith Forsaken",
    "GameName": "Bleak Faith: Forsaken",
    "PoorlyCompressedExtensions": {
      ".mp4": 97,
      ".sfk": 1,
      ".txt": 2
    },
    "SteamID": 1173220,
    "TotalFiles": 2
  },
  {
    "CompressionResults": [
      {
        "AfterBytes": 52912043,
        "BeforeBytes": 79022067,
        "CompType": 3,
        "TotalResults": 2
      }
    ],
    "Confidence": 0,
    "FolderName": "Fap Queen 2",
    "GameName": "Fap Queen 2",
    "PoorlyCompressedExtensions": {
      ".ini": 2,
      ".png": 6
    },
    "SteamID": 1173280,
    "TotalFiles": 2
  },
  {
    "CompressionResults": [
      {
        "AfterBytes": 738288399,
        "BeforeBytes": 858564268,
        "CompType": 3,
        "TotalResults": 1
      }
    ],
    "Confidence": 0,
    "FolderName": "Futa Fix Dick Dine and Dash",
    "GameName": "Futa Fix Dick Dine and Dash",
    "PoorlyCompressedExtensions": {
      ".ini": 1,
      ".shader": 1,
      ".txt": 1
    },
    "SteamID": 1173400,
    "TotalFiles": 1
  },
  {
    "CompressionResults": [
      {
        "AfterBytes": 906564761,
        "BeforeBytes": 1010021309,
        "CompType": 3,
        "TotalResults": 1
      }
    ],
    "Confidence": 0,
    "FolderName": "My Breast Friend Sally",
    "GameName": "My Breast Friend Sally",
    "PoorlyCompressedExtensions": {
      ".ini": 1,
      ".mp4": 3,
      ".shader": 1
    },
    "SteamID": 1173410,
    "TotalFiles": 1
  },
  {
    "CompressionResults": [
      {
        "AfterBytes": 190526703,
        "BeforeBytes": 357559579,
        "CompType": 0,
        "TotalResults": 1
      },
      {
        "AfterBytes": 190276118,
        "BeforeBytes": 477462562,
        "CompType": 3,
        "TotalResults": 8
      }
    ],
    "Confidence": 2,
    "FolderName": "XSOverlay_Beta",
    "GameName": "XSOverlay",
    "PoorlyCompressedExtensions": {
      ".browser": 27,
      ".gitignore": 5,
      ".html": 30,
      ".info": 9,
      ".manifest": 54,
      ".ogg": 142,
      ".png": 67,
      ".resource": 9,
      ".woff": 6,
      ".woff2": 6
    },
    "SteamID": 1173510,
    "TotalFiles": 9
  },
  {
    "CompressionResults": [
      {
        "AfterBytes": 7395528764,
        "BeforeBytes": 7796070099,
        "CompType": 2,
        "TotalResults": 1
      }
    ],
    "Confidence": 0,
    "FolderName": "RE3DEMO",
    "GameName": "Resident Evil 3: Raccoon City Demo ",
    "PoorlyCompressedExtensions": {
      ".bin": 1,
      ".pak": 1
    },
    "SteamID": 1173690,
    "TotalFiles": 1
  },
  {
    "CompressionResults": [
      {
        "AfterBytes": 566891280,
        "BeforeBytes": 634106429,
        "CompType": 0,
        "TotalResults": 1
      },
      {
        "AfterBytes": 545338852,
        "BeforeBytes": 634106429,
        "CompType": 2,
        "TotalResults": 1
      }
    ],
    "Confidence": 0,
    "FolderName": "FINAL FANTASY II PR",
    "GameName": "FINAL FANTASY II",
    "PoorlyCompressedExtensions": {
      ".browser": 6,
      ".bundle": 905,
      ".info": 2,
      ".manifest": 26,
      ".map": 6,
      ".txt": 2
    },
    "SteamID": 1173780,
    "TotalFiles": 2
  },
  {
    "CompressionResults": [
      {
        "AfterBytes": 659971397,
        "BeforeBytes": 741070574,
        "CompType": 1,
        "TotalResults": 1
      },
      {
        "AfterBytes": 454589301,
        "BeforeBytes": 519690808,
        "CompType": 2,
        "TotalResults": 1
      }
    ],
    "Confidence": 0,
    "FolderName": "FINAL FANTASY III PR",
    "GameName": "FINAL FANTASY III",
    "PoorlyCompressedExtensions": {
      ".browser": 6,
      ".bundle": 2399,
      ".info": 2,
      ".manifest": 26,
      ".map": 6,
      ".txt": 2
    },
    "SteamID": 1173790,
    "TotalFiles": 2
  },
  {
    "CompressionResults": [
      {
        "AfterBytes": 615537494,
        "BeforeBytes": 726532912,
        "CompType": 1,
        "TotalResults": 2
      },
      {
        "AfterBytes": 655700196,
        "BeforeBytes": 772119447,
        "CompType": 3,
        "TotalResults": 1
      }
    ],
    "Confidence": 0,
    "FolderName": "FINAL FANTASY IV PR",
    "GameName": "FINAL FANTASY IV",
    "PoorlyCompressedExtensions": {
      ".browser": 12,
      ".bundle": 2924,
      ".info": 3,
      ".manifest": 39,
      ".map": 12,
      ".png": 1,
      ".txt": 2
    },
    "SteamID": 1173800,
    "TotalFiles": 3
  },
  {
    "CompressionResults": [
      {
        "AfterBytes": 817369413,
        "BeforeBytes": 953943697,
        "CompType": 0,
        "TotalResults": 1
      },
      {
        "AfterBytes": 752667761,
        "BeforeBytes": 846171448,
        "CompType": 1,
        "TotalResults": 1
      },
      {
        "AfterBytes": 760275959,
        "BeforeBytes": 898566275,
        "CompType": 3,
        "TotalResults": 1
      }
    ],
    "Confidence": 0,
    "FolderName": "FINAL FANTASY V PR",
    "GameName": "FINAL FANTASY V",
    "PoorlyCompressedExtensions": {
      ".browser": 12,
      ".bundle": 2434,
      ".csv": 1,
      ".info": 3,
      ".manifest": 39,
      ".map": 12,
      ".txt": 2,
      ".zip": 1
    },
    "SteamID": 1173810,
    "TotalFiles": 3
  },
  {
    "CompressionResults": [
      {
        "AfterBytes": 1064668492,
        "BeforeBytes": 1170478628,
        "CompType": 1,
        "TotalResults": 1
      },
      {
        "AfterBytes": 1120925386,
        "BeforeBytes": 1329875960,
        "CompType": 3,
        "TotalResults": 3
      }
    ],
    "Confidence": 0,
    "FolderName": "FINAL FANTASY VI PR",
    "GameName": "FINAL FANTASY VI",
    "PoorlyCompressedExtensions": {
      ".browser": 15,
      ".info": 4,
      ".manifest": 52,
      ".map": 15,
      ".txt": 3
    },
    "SteamID": 1173820,
    "TotalFiles": 4
  },
  {
    "CompressionResults": [
      {
        "AfterBytes": 125182785462,
        "BeforeBytes": 128408372275,
        "CompType": 0,
        "TotalResults": 30
      },
      {
        "AfterBytes": 124082165864,
        "BeforeBytes": 127697251124,
        "CompType": 1,
        "TotalResults": 30
      },
      {
        "AfterBytes": 124886105825,
        "BeforeBytes": 128863282050,
        "CompType": 2,
        "TotalResults": 51
      },
      {
        "AfterBytes": 123404821255,
        "BeforeBytes": 128401524412,
        "CompType": 3,
        "TotalResults": 34
      }
    ],
    "Confidence": 2,
    "FolderName": "Red Dead Redemption 2",
    "GameName": "Red Dead Redemption 2",
    "PoorlyCompressedExtensions": {
      ".rpf": 12703,
      ".vdf": 228
    },
    "SteamID": 1174180,
    "TotalFiles": 145
  },
  {
    "CompressionResults": [
      {
        "AfterBytes": 1012603038,
        "BeforeBytes": 1184103194,
        "CompType": 3,
        "TotalResults": 1
      }
    ],
    "Confidence": 0,
    "FolderName": "Yuletide Legends",
    "GameName": "Yuletide Legends: Who Framed Santa Claus",
    "PoorlyCompressedExtensions": {
      ".sparkconfig": 1,
      ".zip": 1
    },
    "SteamID": 1174500,
    "TotalFiles": 1
  },
  {
    "CompressionResults": [
      {
        "AfterBytes": 626711575,
        "BeforeBytes": 641521613,
        "CompType": 3,
        "TotalResults": 2
      }
    ],
    "Confidence": 0,
    "FolderName": "Tacview",
    "GameName": "Tacview",
    "PoorlyCompressedExtensions": {
      ".dat": 2,
      ".dumb": 2,
      ".md": 34,
      ".mo": 10,
      ".png": 30,
      ".rc": 4,
      ".vdf": 2
    },
    "SteamID": 1174860,
    "TotalFiles": 2
  },
  {
    "CompressionResults": [
      {
        "AfterBytes": 206884963,
        "BeforeBytes": 291478585,
        "CompType": 3,
        "TotalResults": 2
      }
    ],
    "Confidence": 0,
    "FolderName": "Kill or Love",
    "GameName": "Kill or Love",
    "PoorlyCompressedExtensions": {
      ".egg": 12,
      ".manifest": 2,
      ".plist": 2,
      ".rpyb": 6,
      ".sh": 2,
      ".vbs": 2
    },
    "SteamID": 1174940,
    "TotalFiles": 2
  },
  {
    "CompressionResults": [
      {
        "AfterBytes": 505609462,
        "BeforeBytes": 697427064,
        "CompType": 3,
        "TotalResults": 1
      }
    ],
    "Confidence": 0,
    "FolderName": "Vecter",
    "GameName": "Vecter",
    "PoorlyCompressedExtensions": {
      ".config": 1,
      ".info": 1,
      ".jpeg": 1,
      ".jpg": 6,
      ".mp3": 12,
      ".mp4": 5,
      ".png": 14,
      ".resource": 2,
      ".txt": 1
    },
    "SteamID": 1175140,
    "TotalFiles": 1
  },
  {
    "CompressionResults": [
      {
        "AfterBytes": 527596204,
        "BeforeBytes": 550002277,
        "CompType": 3,
        "TotalResults": 1
      }
    ],
    "Confidence": 0,
    "FolderName": "House of 1000 Doors The Palm of Zoroaster",
    "GameName": "House of 1000 Doors: The Palm of Zoroaster",
    "PoorlyCompressedExtensions": {
      "": 1,
      ".jpg": 300,
      ".ogg": 672,
      ".ogv": 19,
      ".pak": 1,
      ".vsh": 1
    },
    "SteamID": 1175160,
    "TotalFiles": 1
  },
  {
    "CompressionResults": [
      {
        "AfterBytes": 4651785416,
        "BeforeBytes": 4691788103,
        "CompType": 0,
        "TotalResults": 1
      }
    ],
    "Confidence": 0,
    "FolderName": "NatsukiChronicles",
    "GameName": "Natsuki Chronicles",
    "PoorlyCompressedExtensions": {
      ".sfa": 60
    },
    "SteamID": 1175190,
    "TotalFiles": 1
  },
  {
    "CompressionResults": [
      {
        "AfterBytes": 398979341,
        "BeforeBytes": 518093950,
        "CompType": 3,
        "TotalResults": 1
      }
    ],
    "Confidence": 0,
    "FolderName": "Revita",
    "GameName": "Revita",
    "PoorlyCompressedExtensions": {
      ".exp": 1,
      ".ini": 1,
      ".lib": 1,
      ".rar": 1,
      ".txt": 1
    },
    "SteamID": 1175460,
    "TotalFiles": 1
  },
  {
    "CompressionResults": [
      {
        "AfterBytes": 9299656702,
        "BeforeBytes": 9816872739,
        "CompType": 0,
        "TotalResults": 2
      },
      {
        "AfterBytes": 9183642057,
        "BeforeBytes": 9816872739,
        "CompType": 2,
        "TotalResults": 1
      }
    ],
    "Confidence": 0,
    "FolderName": "Legend of Mana",
    "GameName": "Legend of Mana",
    "PoorlyCompressedExtensions": {
      "": 678,
      ".m": 14928
    },
    "SteamID": 1175830,
    "TotalFiles": 3
  },
  {
    "CompressionResults": [
      {
        "AfterBytes": 97193520,
        "BeforeBytes": 238522050,
        "CompType": 3,
        "TotalResults": 1
      }
    ],
    "Confidence": 0,
    "FolderName": "Toy Robot",
    "GameName": "Toy Robot",
    "PoorlyCompressedExtensions": {
      ".browser": 3,
      ".info": 1,
      ".map": 3,
      ".resource": 9,
      ".txt": 1
    },
    "SteamID": 1176000,
    "TotalFiles": 1
  },
  {
    "CompressionResults": [
      {
        "AfterBytes": 353503025,
        "BeforeBytes": 689026771,
        "CompType": 3,
        "TotalResults": 1
      }
    ],
    "Confidence": 0,
    "FolderName": "Rampage Miami",
    "GameName": "Rampage Miami",
    "PoorlyCompressedExtensions": {
      ".browser": 1,
      ".info": 1,
      ".map": 1,
      ".resource": 2
    },
    "SteamID": 1176020,
    "TotalFiles": 1
  },
  {
    "CompressionResults": [
      {
        "AfterBytes": 23034195006,
        "BeforeBytes": 25933481561,
        "CompType": 2,
        "TotalResults": 1
      }
    ],
    "Confidence": 0,
    "FolderName": "Terra Invicta",
    "GameName": "Terra Invicta",
    "PoorlyCompressedExtensions": {
      ".bank": 22,
      ".browser": 3,
      ".info": 1,
      ".map": 3
    },
    "SteamID": 1176470,
    "TotalFiles": 1
  },
  {
    "CompressionResults": [
      {
        "AfterBytes": 487955469,
        "BeforeBytes": 845623972,
        "CompType": 2,
        "TotalResults": 1
      },
      {
        "AfterBytes": 446462124,
        "BeforeBytes": 845623972,
        "CompType": 3,
        "TotalResults": 2
      }
    ],
    "Confidence": 0,
    "FolderName": "SpaceCrew",
    "GameName": "Space Crew: Legendary Edition",
    "PoorlyCompressedExtensions": {
      ".browser": 9,
      ".info": 3,
      ".jpg": 3,
      ".map": 9,
      ".png": 24,
      ".resource": 3
    },
    "SteamID": 1176710,
    "TotalFiles": 3
  },
  {
    "CompressionResults": [
      {
        "AfterBytes": 1939814941,
        "BeforeBytes": 5110067210,
        "CompType": 3,
        "TotalResults": 1
      }
    ],
    "Confidence": 0,
    "FolderName": "Transformers",
    "GameName": "TRANSFORMERS: BATTLEGROUNDS",
    "PoorlyCompressedExtensions": {
      ".bank": 7,
      ".browser": 3,
      ".config": 7,
      ".info": 1,
      ".json": 2,
      ".map": 3,
      ".png": 1,
      ".resource": 2,
      ".txt": 1,
      ".xml": 2
    },
    "SteamID": 1177000,
    "TotalFiles": 1
  },
  {
    "CompressionResults": [
      {
        "AfterBytes": 1552655028,
        "BeforeBytes": 1740266832,
        "CompType": 3,
        "TotalResults": 1
      }
    ],
    "Confidence": 0,
    "FolderName": "Memoirs of a Battle Brothel",
    "GameName": "Memoirs of a Battle Brothel",
    "PoorlyCompressedExtensions": {
      ".css": 1,
      ".jpg": 1,
      ".mp3": 5,
      ".png": 3,
      ".rpgmvo": 1362,
      ".rpgmvp": 2720,
      ".rpgsave": 1,
      ".sh": 1,
      ".sumrndmdde": 1,
      ".webm": 7
    },
    "SteamID": 1177380,
    "TotalFiles": 1
  },
  {
    "CompressionResults": [
      {
        "AfterBytes": 790929881,
        "BeforeBytes": 897036946,
        "CompType": 3,
        "TotalResults": 1
      }
    ],
    "Confidence": 0,
    "FolderName": "UncleNeighbor",
    "GameName": "UncleNeighbor",
    "PoorlyCompressedExtensions": {
      ".bundle": 31,
      ".config": 1,
      ".info": 1,
      ".resource": 1,
      ".txt": 2
    },
    "SteamID": 1177420,
    "TotalFiles": 1
  },
  {
    "CompressionResults": [
      {
        "AfterBytes": 112622841,
        "BeforeBytes": 162557401,
        "CompType": 3,
        "TotalResults": 1
      }
    ],
    "Confidence": 0,
    "FolderName": "Yu Escape  Monday",
    "GameName": "Yu Escape / Monday",
    "PoorlyCompressedExtensions": {
      ".browser": 3,
      ".info": 1,
      ".json": 3,
      ".map": 3,
      ".resource": 1
    },
    "SteamID": 1177720,
    "TotalFiles": 1
  },
  {
    "CompressionResults": [
      {
        "AfterBytes": 633657454,
        "BeforeBytes": 1378218009,
        "CompType": 2,
        "TotalResults": 1
      },
      {
        "AfterBytes": 542140032,
        "BeforeBytes": 1349305966,
        "CompType": 3,
        "TotalResults": 2
      }
    ],
    "Confidence": 0,
    "FolderName": "LittleKittyBigCity",
    "GameName": "Little Kitty, Big City",
    "PoorlyCompressedExtensions": {
      ".Config": 1,
      ".browser": 9,
      ".config": 7,
      ".info": 3,
      ".lnk": 6,
      ".map": 9,
      ".txt": 3,
      ".xml": 2
    },
    "SteamID": 1177980,
    "TotalFiles": 3
  },
  {
    "CompressionResults": [
      {
        "AfterBytes": 311296167,
        "BeforeBytes": 819787603,
        "CompType": 0,
        "TotalResults": 1
      },
      {
        "AfterBytes": 282572684,
        "BeforeBytes": 819787603,
        "CompType": 1,
        "TotalResults": 1
      },
      {
        "AfterBytes": 267399991,
        "BeforeBytes": 819787603,
        "CompType": 2,
        "TotalResults": 1
      },
      {
        "AfterBytes": 228909073,
        "BeforeBytes": 819788114,
        "CompType": 3,
        "TotalResults": 2
      }
    ],
    "Confidence": 0,
    "FolderName": "Star Fetchers Pilot",
    "GameName": "Star Fetchers",
    "PoorlyCompressedExtensions": {
      ".config": 15,
      ".data": 5,
      ".dtree": 75,
      ".mgfx": 10,
      ".mp4": 10,
      ".ogg": 95,
      ".png": 320,
      ".txt": 10
    },
    "SteamID": 1178030,
    "TotalFiles": 5
  },
  {
    "CompressionResults": [
      {
        "AfterBytes": 673510671,
        "BeforeBytes": 2400919640,
        "CompType": 2,
        "TotalResults": 1
      },
      {
        "AfterBytes": 571617608,
        "BeforeBytes": 2400919640,
        "CompType": 3,
        "TotalResults": 1
      }
    ],
    "Confidence": 0,
    "FolderName": "Stirring Abyss",
    "GameName": "Stirring Abyss",
    "PoorlyCompressedExtensions": {
      ".Config": 2,
      ".browser": 6,
      ".config": 9,
      ".cs": 1,
      ".info": 2,
      ".jpg": 2,
      ".map": 6,
      ".ogg": 2,
      ".pdf": 2,
      ".png": 42,
      ".resource": 8,
      ".resx": 8,
      ".txt": 2,
      ".wav": 1,
      ".xml": 1
    },
    "SteamID": 1178210,
    "TotalFiles": 2
  },
  {
    "CompressionResults": [
      {
        "AfterBytes": 2977182273,
        "BeforeBytes": 3095597267,
        "CompType": 0,
        "TotalResults": 1
      },
      {
        "AfterBytes": 2921227339,
        "BeforeBytes": 3095597267,
        "CompType": 3,
        "TotalResults": 1
      }
    ],
    "Confidence": 0,
    "FolderName": "ICBM",
    "GameName": "ICBM",
    "PoorlyCompressedExtensions": {
      ".Config": 2,
      ".e5i": 10,
      ".e5p": 10,
      ".glsl": 24,
      ".hlsl": 24,
      ".jpg": 6,
      ".num": 20,
      ".ogg": 24,
      ".pdf": 2,
      ".rnt": 20,
      ".table": 14
    },
    "SteamID": 1178220,
    "TotalFiles": 2
  },
  {
    "CompressionResults": [
      {
        "AfterBytes": 6157750272,
        "BeforeBytes": 15181115170,
        "CompType": 3,
        "TotalResults": 1
      }
    ],
    "Confidence": 0,
    "FolderName": "ParanormalHK",
    "GameName": "ParanormalHK",
    "PoorlyCompressedExtensions": {
      ".mp4": 4
    },
    "SteamID": 1178490,
    "TotalFiles": 1
  },
  {
    "CompressionResults": [
      {
        "AfterBytes": 2739420583,
        "BeforeBytes": 8084832392,
        "CompType": 2,
        "TotalResults": 2
      }
    ],
    "Confidence": 0,
    "FolderName": "BattleGroupVR",
    "GameName": "BattleGroupVR",
    "PoorlyCompressedExtensions": {
      ".asset": 2,
      ".browser": 6,
      ".conf": 8,
      ".ie": 2,
      ".info": 2,
      ".int": 4,
      ".json": 36,
      ".map": 6,
      ".mat": 2,
      ".stats": 2
    },
    "SteamID": 1178780,
    "TotalFiles": 2
  },
  {
    "CompressionResults": [
      {
        "AfterBytes": 356422161,
        "BeforeBytes": 424433773,
        "CompType": 2,
        "TotalResults": 1
      }
    ],
    "Confidence": 0,
    "FolderName": "shirenthewanderer5plus",
    "GameName": "Shiren the Wanderer: The Tower of Fortune and the Dice of Fate",
    "PoorlyCompressedExtensions": {
      ".txt": 1,
      ".vdf": 1
    },
    "SteamID": 1178790,
    "TotalFiles": 1
  },
  {
    "CompressionResults": [
      {
        "AfterBytes": 11442400543,
        "BeforeBytes": 11550289064,
        "CompType": 0,
        "TotalResults": 1
      },
      {
        "AfterBytes": 11332840382,
        "BeforeBytes": 11503192266,
        "CompType": 2,
        "TotalResults": 6
      },
      {
        "AfterBytes": 11365938683,
        "BeforeBytes": 11577279021,
        "CompType": 3,
        "TotalResults": 3
      }
    ],
    "Confidence": 2,
    "FolderName": "BrightMemoryInfinite",
    "GameName": "Bright Memory: Infinite",
    "PoorlyCompressedExtensions": {
      ".lnk": 6,
      ".mp4": 390,
      ".pak": 32
    },
    "SteamID": 1178830,
    "TotalFiles": 10
  },
  {
    "CompressionResults": [
      {
        "AfterBytes": 5540289945,
        "BeforeBytes": 7495543802,
        "CompType": 0,
        "TotalResults": 2
      },
      {
        "AfterBytes": 5207377735,
        "BeforeBytes": 7495543802,
        "CompType": 2,
        "TotalResults": 1
      },
      {
        "AfterBytes": 4719196654,
        "BeforeBytes": 7495543802,
        "CompType": 3,
        "TotalResults": 2
      }
    ],
    "Confidence": 0,
    "FolderName": "Panzer Dragoon Remake",
    "GameName": "Panzer Dragoon: Remake",
    "PoorlyCompressedExtensions": {
      ".browser": 15,
      ".info": 5,
      ".map": 15,
      ".png": 5,
      ".resource": 100,
      ".txt": 10
    },
    "SteamID": 1178880,
    "TotalFiles": 5
  },
  {
    "CompressionResults": [
      {
        "AfterBytes": 5289572185,
        "BeforeBytes": 5351282210,
        "CompType": 1,
        "TotalResults": 1
      }
    ],
    "Confidence": 0,
    "FolderName": "Wing of darkness",
    "GameName": "\u6709\u7ffc\u306e\u30d5\u30ed\u30a4\u30e9\u30a4\u30f3 Wing of Darkness",
    "PoorlyCompressedExtensions": {
      ".bank": 2,
      ".mp4": 5,
      ".pak": 1,
      ".uasset": 24
    },
    "SteamID": 1179060,
    "TotalFiles": 1
  },
  {
    "CompressionResults": [
      {
        "AfterBytes": 734157244,
        "BeforeBytes": 790169985,
        "CompType": 2,
        "TotalResults": 1
      },
      {
        "AfterBytes": 676290393,
        "BeforeBytes": 732674018,
        "CompType": 3,
        "TotalResults": 3
      }
    ],
    "Confidence": 0,
    "FolderName": "FAITH",
    "GameName": "FAITH",
    "PoorlyCompressedExtensions": {
      ".MOV": 36,
      ".PNG": 8,
      ".csv": 4,
      ".gif": 53,
      ".ini": 5,
      ".jpg": 156,
      ".mp4": 32,
      ".ogg": 12,
      ".pdf": 8,
      ".png": 86,
      ".txt": 4
    },
    "SteamID": 1179080,
    "TotalFiles": 4
  },
  {
    "CompressionResults": [
      {
        "AfterBytes": 416565757,
        "BeforeBytes": 501012422,
        "CompType": 3,
        "TotalResults": 1
      }
    ],
    "Confidence": 0,
    "FolderName": "OppaidiusTC",
    "GameName": "Oppaidius Tropical Cruise!",
    "PoorlyCompressedExtensions": {
      ".egg": 6,
      ".icns": 1,
      ".manifest": 1,
      ".plist": 1,
      ".png": 6,
      ".rpyb": 3,
      ".sh": 1,
      ".vbs": 1
    },
    "SteamID": 1179100,
    "TotalFiles": 1
  },
  {
    "CompressionResults": [
      {
        "AfterBytes": 1256218057,
        "BeforeBytes": 1799772068,
        "CompType": 2,
        "TotalResults": 1
      },
      {
        "AfterBytes": 1695598252,
        "BeforeBytes": 2364980774,
        "CompType": 3,
        "TotalResults": 2
      }
    ],
    "Confidence": 0,
    "FolderName": "Kill It With Fire",
    "GameName": "Kill It With Fire",
    "PoorlyCompressedExtensions": {
      ".mp4": 15,
      ".pak": 3,
      ".tps": 3,
      ".txt": 6
    },
    "SteamID": 1179210,
    "TotalFiles": 3
  },
  {
    "CompressionResults": [
      {
        "AfterBytes": 186761216,
        "BeforeBytes": 288270069,
        "CompType": 3,
        "TotalResults": 1
      }
    ],
    "Confidence": 0,
    "FolderName": "Gachi Heroes 2 Flexboll",
    "GameName": "Gachi Heroes 2: Flexboll",
    "PoorlyCompressedExtensions": {
      ".nw": 1
    },
    "SteamID": 1179560,
    "TotalFiles": 1
  },
  {
    "CompressionResults": [
      {
        "AfterBytes": 3632920337,
        "BeforeBytes": 3739813422,
        "CompType": 3,
        "TotalResults": 1
      }
    ],
    "Confidence": 0,
    "FolderName": "Pull Stay",
    "GameName": "Pull Stay",
    "PoorlyCompressedExtensions": {
      ".mp4": 2,
      ".pak": 2,
      ".txt": 1
    },
    "SteamID": 1179890,
    "TotalFiles": 1
  },
  {
    "CompressionResults": [
      {
        "AfterBytes": 2057380929,
        "BeforeBytes": 3227253415,
        "CompType": 2,
        "TotalResults": 1
      }
    ],
    "Confidence": 0,
    "FolderName": "Manor of Mystic Courtesans",
    "GameName": "Manor of Mystic Courtesans",
    "PoorlyCompressedExtensions": {
      ".browser": 3,
      ".info": 1,
      ".map": 3,
      ".resource": 2
    },
    "SteamID": 1180330,
    "TotalFiles": 1
  },
  {
    "CompressionResults": [
      {
        "AfterBytes": 9593989235,
        "BeforeBytes": 9836789236,
        "CompType": 0,
        "TotalResults": 1
      },
      {
        "AfterBytes": 13044038281,
        "BeforeBytes": 13235241574,
        "CompType": 2,
        "TotalResults": 1
      }
    ],
    "Confidence": 0,
    "FolderName": "sogame",
    "GameName": "Stay Out",
    "PoorlyCompressedExtensions": {
      ".bat": 6,
      ".cer": 3,
      ".json": 7,
      ".png": 1,
      ".pyson": 3,
      ".so": 107,
      ".txt": 6,
      ".vdf": 2,
      ".xdds": 7
    },
    "SteamID": 1180380,
    "TotalFiles": 2
  },
  {
    "CompressionResults": [
      {
        "AfterBytes": 19063547384,
        "BeforeBytes": 19339246573,
        "CompType": 1,
        "TotalResults": 1
      },
      {
        "AfterBytes": 19028477432,
        "BeforeBytes": 19339246573,
        "CompType": 2,
        "TotalResults": 2
      },
      {
        "AfterBytes": 18926433803,
        "BeforeBytes": 19339246592,
        "CompType": 3,
        "TotalResults": 1
      }
    ],
    "Confidence": 0,
    "FolderName": "TellMeWhy",
    "GameName": "Tell Me Why",
    "PoorlyCompressedExtensions": {
      ".pak": 304,
      ".vdf": 4
    },
    "SteamID": 1180660,
    "TotalFiles": 4
  },
  {
    "CompressionResults": [
      {
        "AfterBytes": 620540002,
        "BeforeBytes": 657488816,
        "CompType": 3,
        "TotalResults": 1
      }
    ],
    "Confidence": 0,
    "FolderName": "UBERMOSH_OMEGA",
    "GameName": "UBERMOSH:OMEGA",
    "PoorlyCompressedExtensions": {
      ".ini": 1,
      ".mp3": 1,
      ".png": 1
    },
    "SteamID": 1181000,
    "TotalFiles": 1
  },
  {
    "CompressionResults": [
      {
        "AfterBytes": 132284048,
        "BeforeBytes": 293751986,
        "CompType": 3,
        "TotalResults": 1
      }
    ],
    "Confidence": 0,
    "FolderName": "JetboardJoust",
    "GameName": "Jetboard Joust",
    "PoorlyCompressedExtensions": {
      ".config": 2,
      ".md": 1,
      ".ogg": 10
    },
    "SteamID": 1181600,
    "TotalFiles": 1
  },
  {
    "CompressionResults": [
      {
        "AfterBytes": 6154263919,
        "BeforeBytes": 10637671554,
        "CompType": 0,
        "TotalResults": 1
      }
    ],
    "Confidence": 0,
    "FolderName": "Weed Shop 3",
    "GameName": "Weed Shop 3",
    "PoorlyCompressedExtensions": {
      ".bin": 2,
      ".browser": 3,
      ".info": 1,
      ".map": 3,
      ".resource": 8
    },
    "SteamID": 1182110,
    "TotalFiles": 1
  },
  {
    "CompressionResults": [
      {
        "AfterBytes": 894532040,
        "BeforeBytes": 1166815494,
        "CompType": 2,
        "TotalResults": 1
      },
      {
        "AfterBytes": 840153544,
        "BeforeBytes": 1166815494,
        "CompType": 3,
        "TotalResults": 2
      }
    ],
    "Confidence": 0,
    "FolderName": "The Excavation of Hob's Barrow",
    "GameName": "The Excavation of Hob's Barrow",
    "PoorlyCompressedExtensions": {
      ".cfg": 3,
      ".txt": 3,
      ".vox": 6
    },
    "SteamID": 1182310,
    "TotalFiles": 3
  },
  {
    "CompressionResults": [
      {
        "AfterBytes": 740121631,
        "BeforeBytes": 898185643,
        "CompType": 3,
        "TotalResults": 1
      }
    ],
    "Confidence": 0,
    "FolderName": "Impostor Factory",
    "GameName": "Impostor Factory",
    "PoorlyCompressedExtensions": {
      ".PNG": 2,
      ".browser": 3,
      ".conf": 1,
      ".info": 1,
      ".map": 3,
      ".mp3": 1,
      ".ogg": 799,
      ".png": 366,
      ".resource": 1,
      ".rgssad": 1
    },
    "SteamID": 1182620,
    "TotalFiles": 1
  },
  {
    "CompressionResults": [
      {
        "AfterBytes": 173926731,
        "BeforeBytes": 1033227924,
        "CompType": 3,
        "TotalResults": 1
      }
    ],
    "Confidence": 0,
    "FolderName": "QT",
    "GameName": "QT",
    "PoorlyCompressedExtensions": {
      ".browser": 3,
      ".info": 1,
      ".map": 3,
      ".png": 1,
      ".resource": 6,
      ".txt": 1
    },
    "SteamID": 1182830,
    "TotalFiles": 1
  },
  {
    "CompressionResults": [
      {
        "AfterBytes": 51201215602,
        "BeforeBytes": 52002373349,
        "CompType": 1,
        "TotalResults": 2
      },
      {
        "AfterBytes": 50795146136,
        "BeforeBytes": 51676308836,
        "CompType": 2,
        "TotalResults": 3
      },
      {
        "AfterBytes": 51034704644,
        "BeforeBytes": 52243660886,
        "CompType": 3,
        "TotalResults": 3
      }
    ],
    "Confidence": 0,
    "FolderName": "A Plague Tale Requiem",
    "GameName": "A Plague Tale: Requiem",
    "PoorlyCompressedExtensions": {
      ".DPC": 1511,
      ".PCK": 150,
      ".bin": 8,
      ".mp4": 304,
      ".names": 5,
      ".tsc": 16
    },
    "SteamID": 1182900,
    "TotalFiles": 8
  },
  {
    "CompressionResults": [
      {
        "AfterBytes": 338665163,
        "BeforeBytes": 607106755,
        "CompType": 0,
        "TotalResults": 1
      }
    ],
    "Confidence": 0,
    "FolderName": "Holoswitch",
    "GameName": "Holoswitch",
    "PoorlyCompressedExtensions": {
      ".browser": 3,
      ".info": 1,
      ".map": 3,
      ".resource": 1,
      ".vdf": 1,
      ".vrmanifest": 1
    },
    "SteamID": 1183720,
    "TotalFiles": 1
  },
  {
    "CompressionResults": [
      {
        "AfterBytes": 956102970,
        "BeforeBytes": 2541641602,
        "CompType": 2,
        "TotalResults": 1
      }
    ],
    "Confidence": 0,
    "FolderName": "Shardpunk Verminfall",
    "GameName": "Shardpunk",
    "PoorlyCompressedExtensions": {
      ".browser": 6,
      ".info": 2,
      ".json": 4,
      ".map": 6,
      ".meta": 39,
      ".resource": 2,
      ".vdf": 2
    },
    "SteamID": 1183800,
    "TotalFiles": 1
  },
  {
    "CompressionResults": [
      {
        "AfterBytes": 12692942229,
        "BeforeBytes": 13050100633,
        "CompType": 3,
        "TotalResults": 1
      }
    ],
    "Confidence": 0,
    "FolderName": "Scavengers",
    "GameName": "Scavengers",
    "PoorlyCompressedExtensions": {
      ".bat": 1,
      ".cer": 1,
      ".json": 2,
      ".pak": 2,
      ".sig": 1,
      ".tps": 1,
      ".txt": 1,
      ".uasset": 1,
      ".vdf": 1
    },
    "SteamID": 1183940,
    "TotalFiles": 1
  },
  {
    "CompressionResults": [
      {
        "AfterBytes": 31256551336,
        "BeforeBytes": 31661235600,
        "CompType": 0,
        "TotalResults": 1
      }
    ],
    "Confidence": 0,
    "FolderName": "GearsTactics",
    "GameName": "Gears Tactics",
    "PoorlyCompressedExtensions": {
      ".b2container": 41,
      ".bk2": 4,
      ".config": 1,
      ".log": 1
    },
    "SteamID": 1184050,
    "TotalFiles": 1
  },
  {
    "CompressionResults": [
      {
        "AfterBytes": 19822934646,
        "BeforeBytes": 20262667300,
        "CompType": 2,
        "TotalResults": 6
      },
      {
        "AfterBytes": 15466567644,
        "BeforeBytes": 16011168230,
        "CompType": 3,
        "TotalResults": 1
      }
    ],
    "Confidence": 2,
    "FolderName": "KartRider Drift",
    "GameName": "KartRider: Drift",
    "PoorlyCompressedExtensions": {
      ".bank": 994,
      ".mp4": 400,
      ".pak": 558,
      ".png": 14
    },
    "SteamID": 1184140,
    "TotalFiles": 7
  },
  {
    "CompressionResults": [
      {
        "AfterBytes": 10960057323,
        "BeforeBytes": 12224240698,
        "CompType": 3,
        "TotalResults": 1
      }
    ],
    "Confidence": 0,
    "FolderName": "RUSSIAPHOBIA",
    "GameName": "RUSSIAPHOBIA",
    "PoorlyCompressedExtensions": {
      ".browser": 6,
      ".info": 2,
      ".map": 6,
      ".resource": 19,
      ".txt": 5
    },
    "SteamID": 1184160,
    "TotalFiles": 1
  },
  {
    "CompressionResults": [
      {
        "AfterBytes": 31952066715,
        "BeforeBytes": 34496912560,
        "CompType": 0,
        "TotalResults": 3
      },
      {
        "AfterBytes": 30517484521,
        "BeforeBytes": 33749602720,
        "CompType": 1,
        "TotalResults": 7
      },
      {
        "AfterBytes": 35328826321,
        "BeforeBytes": 39568182490,
        "CompType": 2,
        "TotalResults": 9
      },
      {
        "AfterBytes": 35505073715,
        "BeforeBytes": 41375119620,
        "CompType": 3,
        "TotalResults": 5
      }
    ],
    "Confidence": 2,
    "FolderName": "Pathfinder Second Adventure",
    "GameName": "Pathfinder: Wrath of the Righteous - Enhanced Edition",
    "PoorlyCompressedExtensions": {
      ".bat": 46,
      ".bnk": 1053,
      ".browser": 72,
      ".ee": 59394,
      ".info": 72,
      ".map": 72,
      ".nav": 4301,
      ".png": 1078,
      ".terrainlayers": 417
    },
    "SteamID": 1184370,
    "TotalFiles": 24
  }
]